setup.py
dist_gauss_bino/Binomialdistribution.py
dist_gauss_bino/Gaussiandistribution.py
dist_gauss_bino/Generaldistribution.py
dist_gauss_bino/__init__.py
dist_gauss_bino.egg-info/PKG-INFO
dist_gauss_bino.egg-info/SOURCES.txt
dist_gauss_bino.egg-info/dependency_links.txt
dist_gauss_bino.egg-info/not-zip-safe
dist_gauss_bino.egg-info/top_level.txt