Metadata-Version: 1.0
Name: dist-gauss-bino
Version: 0.1
Summary: Gaussian distributions
Home-page: UNKNOWN
Author: Medha Mathur
Author-email: medhamathur27@gmail.com
License: UNKNOWN
Platform: UNKNOWN
